opreport/fonts/DejaVuMathTeXGyre.ttf
opreport/fonts/DejaVuSans-Bold.ttf
opreport/fonts/DejaVuSans-BoldOblique.ttf
opreport/fonts/DejaVuSans-ExtraLight.ttf
opreport/fonts/DejaVuSans-Oblique.ttf
opreport/fonts/DejaVuSans.ttf
opreport/fonts/DejaVuSansCondensed-Bold.ttf
opreport/fonts/DejaVuSansCondensed-BoldOblique.ttf
opreport/fonts/DejaVuSansCondensed-Oblique.ttf
opreport/fonts/DejaVuSansCondensed.ttf
opreport/fonts/DejaVuSansMono-Bold.ttf
opreport/fonts/DejaVuSansMono-BoldOblique.ttf
opreport/fonts/DejaVuSansMono-Oblique.ttf
opreport/fonts/DejaVuSansMono.ttf
opreport/fonts/DejaVuSerif-Bold.ttf
opreport/fonts/DejaVuSerif-BoldItalic.ttf
opreport/fonts/DejaVuSerif-Italic.ttf
opreport/fonts/DejaVuSerif.ttf
opreport/fonts/DejaVuSerifCondensed-Bold.ttf
opreport/fonts/DejaVuSerifCondensed-BoldItalic.ttf
opreport/fonts/DejaVuSerifCondensed-Italic.ttf
opreport/fonts/DejaVuSerifCondensed.ttf
opreport/hardware_inventory_report.py
opreport/helpers.py
opreport/metrics.py
opreport/network_utilization_report.py
opreport/objects.py
opreport/opsramp.py
opreport/patch_management_report.py
opreport/patching.py
opreport/remote_control_usage_report.py
opreport/reportutil.py
opreport/sample-logo.jpeg
opreport/software_inventory_report.py
opreport/utilization_comparison_report.py
opreport-0.3.11.dist-info/entry_points.txt
opreport-0.3.11.dist-info/WHEEL
opreport-0.3.11.dist-info/METADATA
opreport-0.3.11.dist-info/RECORD
