Metadata-Version: 2.1
Name: opreport
Version: 0.3.11
Summary: Some useful multi-tenant pdf reports for OpsRamp
License: MIT
Author: Michael Friedhoff
Author-email: michael.friedhoff@opsramp.com
Maintainer: Michael Friedhoff
Maintainer-email: michael.friedhoff@opsramp.com
Requires-Python: >=3.8,<4.0
Classifier: License :: OSI Approved :: MIT License
Classifier: Programming Language :: Python :: 3
Classifier: Programming Language :: Python :: 3.10
Classifier: Programming Language :: Python :: 3.8
Classifier: Programming Language :: Python :: 3.9
Requires-Dist: DateTime (>=4.4,<5.0)
Requires-Dist: PyYAML (>=6.0,<7.0)
Requires-Dist: XlsxWriter (>=3.0.3,<4.0.0)
Requires-Dist: appdirs (>=1.4.4,<2.0.0)
Requires-Dist: argparse (>=1.4.0,<2.0.0)
Requires-Dist: fpdf2 (>=2.5.0,<3.0.0)
Requires-Dist: json5 (>=0.9.6,<0.10.0)
Requires-Dist: matplotlib (>=3.5.1,<4.0.0)
Requires-Dist: numpy (>=1.22.2,<2.0.0)
Requires-Dist: pandas (>=1.4.1,<2.0.0)
Requires-Dist: requests (>=2.27.1,<3.0.0)
